news_publisher/__init__.py
news_publisher/api_server.py
news_publisher/db_server.py
aij_news_publisher-1.0.8.dist-info/LICENSE.txt
aij_news_publisher-1.0.8.dist-info/METADATA
aij_news_publisher-1.0.8.dist-info/WHEEL
aij_news_publisher-1.0.8.dist-info/entry_points.txt
aij_news_publisher-1.0.8.dist-info/top_level.txt
aij_news_publisher-1.0.8.dist-info/RECORD
